gp/portal/__init__.py
gp/portal/cache.py
gp/portal/config.py
gp/portal/api/__init__.py
gp/portal/root/__init__.py
gp/portal/root/templates/index.html
gp/portal/templates/index.html
gp_portal-0.0.4.dist-info/AUTHORS
gp_portal-0.0.4.dist-info/METADATA
gp_portal-0.0.4.dist-info/WHEEL
gp_portal-0.0.4.dist-info/pbr.json
gp_portal-0.0.4.dist-info/top_level.txt
gp_portal-0.0.4.dist-info/RECORD
