Metadata-Version: 2.1
Name: gp-portal
Version: 0.0.4
Summary: gp-portal
Author: hil
Author-email: hil@carota.ai
Classifier: Programming Language :: Python :: 3
Classifier: Operating System :: OS Independent
License-File: AUTHORS
Requires-Dist: flask
Requires-Dist: flask-caching
Requires-Dist: loguru
Requires-Dist: requests
Requires-Dist: python-dotenv
Requires-Dist: gp-flask-ext
